{
  "metadata": {
    "system": "BLITZAR",
    "revision": "2026-03-22",
    "revision_note": "Pinned CI action/tool versions for prod-facing workflows, kept release-lane deterministic subset explicit, and separated prod release evidence from the dev desktop GUI installer artifact."
  },
  "includes": [
    "manifest/evidence.json",
    "manifest/policies.json",
    "manifest/requirements.json",
    "manifest/deviations.json",
    "manifest/fmea_actions.json",
    "manifest/numerical_campaign.json",
    "manifest/test_groups_core.json",
    "manifest/crosswalk.json"
  ]
}
